pysdl2/LoadDLL.py
pysdl2/SDL.py
pysdl2/SDL_assert.py
pysdl2/SDL_audio.py
pysdl2/SDL_blendmode.py
pysdl2/SDL_clipboard.py
pysdl2/SDL_cpuinfo.py
pysdl2/SDL_error.py
pysdl2/SDL_events.py
pysdl2/SDL_filesystem.py
pysdl2/SDL_gamecontroller.py
pysdl2/SDL_gesture.py
pysdl2/SDL_guid.py
pysdl2/SDL_haptic.py
pysdl2/SDL_hidapi.py
pysdl2/SDL_hints.py
pysdl2/SDL_image.py
pysdl2/SDL_joystick.py
pysdl2/SDL_keyboard.py
pysdl2/SDL_keycode.py
pysdl2/SDL_loadso.py
pysdl2/SDL_locale.py
pysdl2/SDL_log.py
pysdl2/SDL_main.py
pysdl2/SDL_messagebox.py
pysdl2/SDL_metal.py
pysdl2/SDL_misc.py
pysdl2/SDL_mixer.py
pysdl2/SDL_mouse.py
pysdl2/SDL_pixels.py
pysdl2/SDL_platform.py
pysdl2/SDL_power.py
pysdl2/SDL_rect.py
pysdl2/SDL_render.py
pysdl2/SDL_rwops.py
pysdl2/SDL_scancode.py
pysdl2/SDL_sensor.py
pysdl2/SDL_shape.py
pysdl2/SDL_surface.py
pysdl2/SDL_syswm.py
pysdl2/SDL_timer.py
pysdl2/SDL_touch.py
pysdl2/SDL_ttf.py
pysdl2/SDL_version.py
pysdl2/SDL_video.py
pysdl2/__init__.py
pysdl2/sdl2.py
pysdl230-0.1.dist-info/METADATA
pysdl230-0.1.dist-info/WHEEL
pysdl230-0.1.dist-info/top_level.txt
pysdl230-0.1.dist-info/RECORD
