Metadata-Version: 2.1
Name: pysdl230
Version: 0.1
Summary: UNKNOWN
Home-page: UNKNOWN
License: UNKNOWN
Platform: UNKNOWN
Requires-Python: >=2.7, <4
